datkit/__init__.py
datkit/_check_times.py
datkit/_datkit_version.py
datkit/_points.py
datkit/_smoothing.py
datkit/_spectral.py
datkit/tests/__init__.py
datkit/tests/test_check_times.py
datkit/tests/test_points.py
datkit/tests/test_smoothing.py
datkit/tests/test_spectral.py
datkit-0.1.1.dist-info/licenses/LICENSE
datkit-0.1.1.dist-info/METADATA
datkit-0.1.1.dist-info/WHEEL
datkit-0.1.1.dist-info/top_level.txt
datkit-0.1.1.dist-info/RECORD
