Metadata-Version: 2.4
Name: datkit
Version: 0.1.1
Summary: A bunch of scripts
Author: Michael Clerx
Author-email: michael@myokit.org
License: BSD 3-clause license
Project-URL: Bug Tracker, https://github.com/myokit/datkit/issues
Project-URL: Documentation, http://datkit.readthedocs.io/
Project-URL: Source Code, https://github.com/myokit/datkit
Classifier: Development Status :: 2 - Pre-Alpha
Classifier: Intended Audience :: Science/Research
Classifier: License :: OSI Approved :: BSD License
Classifier: Operating System :: OS Independent
Classifier: Programming Language :: Python :: 3
Classifier: Topic :: Scientific/Engineering
Requires-Python: >=3.7
License-File: LICENSE
Requires-Dist: numpy
Provides-Extra: docs
Requires-Dist: sphinx>=1.7.4; extra == "docs"
Provides-Extra: dev
Requires-Dist: coverage; extra == "dev"
Requires-Dist: flake8>=3; extra == "dev"
Dynamic: author
Dynamic: author-email
Dynamic: classifier
Dynamic: description
Dynamic: description-content-type
Dynamic: license
Dynamic: license-file
Dynamic: project-url
Dynamic: provides-extra
Dynamic: requires-dist
Dynamic: requires-python
Dynamic: summary
